main.py
mseep_verifiers-0.1.1.dist-info/METADATA
mseep_verifiers-0.1.1.dist-info/WHEEL
mseep_verifiers-0.1.1.dist-info/entry_points.txt
mseep_verifiers-0.1.1.dist-info/top_level.txt
mseep_verifiers-0.1.1.dist-info/RECORD
