Metadata-Version: 2.4
Name: mseep-verifiers
Version: 0.1.1
Summary: Add your description here
Author-email: mseep <support@skydeck.ai>
Requires-Python: >=3.11
Requires-Dist: datasets>=3.2.0
Requires-Dist: fastapi>=0.115.8
Requires-Dist: jinja2>=3.1.5
Requires-Dist: mlx-lm>=0.21.1
Requires-Dist: ollama>=0.4.7
Requires-Dist: pronouncing>=0.2.0
Requires-Dist: pytest>=8.3.4
Requires-Dist: setuptools>=75.8.0
Requires-Dist: uvicorn>=0.34.0
